clpm/__init__.py
clpm/main.py
clpm/sql_utils.py
clpm/utils.py
clpm-1.3.6.dist-info/METADATA
clpm-1.3.6.dist-info/WHEEL
clpm-1.3.6.dist-info/entry_points.txt
clpm-1.3.6.dist-info/top_level.txt
clpm-1.3.6.dist-info/RECORD
