Metadata-Version: 2.1
Name: clpm
Version: 1.3.6
Summary: A command-line password manager
Home-page: https://github.com/alexjaniak/clpm
Author: alexjaniak
License: MIT 2021
Platform: UNKNOWN
Requires-Dist: Click
Requires-Dist: prettytable
Requires-Dist: pycryptodome
